databend_py/VERSION
databend_py/__init__.py
databend_py/client.py
databend_py/connection.py
databend_py/context.py
databend_py/datetypes.py
databend_py/defines.py
databend_py/errors.py
databend_py/log.py
databend_py/result.py
databend_py/retry.py
databend_py/sdk_info.py
databend_py/uploader.py
databend_py/util/__init__.py
databend_py/util/escape.py
databend_py/util/helper.py
databend_py-0.6.4.dist-info/LICENSE
databend_py-0.6.4.dist-info/METADATA
databend_py-0.6.4.dist-info/WHEEL
databend_py-0.6.4.dist-info/top_level.txt
databend_py-0.6.4.dist-info/RECORD
