Metadata-Version: 2.1
Name: databend-py
Version: 0.6.4
Summary: Add your description here
Home-page: https://github.com/databendcloud/databend-py
Author: Databend Cloud Team
Author-email: hantmac@outlook.com
License: Apache License
Keywords: databend db database cloud analytics
Classifier: Development Status :: 4 - Beta
Classifier: Environment :: Console
Classifier: Intended Audience :: Developers
Classifier: Intended Audience :: Information Technology
Classifier: Operating System :: OS Independent
Classifier: Programming Language :: SQL
Classifier: Programming Language :: Python :: 3.9
Classifier: Programming Language :: Python :: 3.10
Classifier: Programming Language :: Python :: 3.11
Classifier: Programming Language :: Python :: 3.12
Classifier: Programming Language :: Python :: Implementation :: PyPy
Classifier: Topic :: Database
Classifier: Topic :: Software Development
Classifier: Topic :: Software Development :: Libraries
Classifier: Topic :: Software Development :: Libraries :: Application Frameworks
Classifier: Topic :: Software Development :: Libraries :: Python Modules
Classifier: Topic :: Scientific/Engineering :: Information Analysis
Requires-Python: >=3.4, <4
License-File: LICENSE
Requires-Dist: black (>=24.10.0)
Requires-Dist: databend-driver (>=0.23.2)
Requires-Dist: environs (>=11.2.1)
Requires-Dist: pytz (>=2024.2)
Requires-Dist: requests (>=2.32.3)
Requires-Dist: setuptools (>=75.6.0)
